Metadata-Version: 1.0
Name: dists
Version: 0.2
Summary: Binomial and Gaussian distributions
Home-page: UNKNOWN
Author: UNKNOWN
Author-email: UNKNOWN
License: UNKNOWN
Platform: UNKNOWN
